monster/__init__.py
monster/monster.py
monster-0.0.1.dist-info/LICENSE
monster-0.0.1.dist-info/METADATA
monster-0.0.1.dist-info/WHEEL
monster-0.0.1.dist-info/top_level.txt
monster-0.0.1.dist-info/RECORD
