Metadata-Version: 1.0
Name: monster
Version: 0.0.1
Summary: include some useful tools, alg, sys
Home-page: UNKNOWN
Author: mazewu
Author-email: mazewu1102@gmail.com
License: UNKNOWN
Platform: UNKNOWN
